{"stats":{"minecraft:picked_up":{"minecraft:paper":2},"minecraft:used":{"minecraft:polished_blackstone_bricks":163,"minecraft:polished_deepslate_slab":1,"minecraft:written_book":8,"minecraft:command_block":2,"minecraft:deepslate_tile_stairs":170,"minecraft:grass_block":1,"minecraft:carrot_on_a_stick":1826,"minecraft:barrier":6,"minecraft:oak_sign":1,"minecraft:stone_button":1,"minecraft:deepslate_tile_slab":10,"minecraft:acacia_wood":2,"minecraft:polished_basalt":323,"minecraft:warped_button":2},"minecraft:dropped":{"minecraft:paper":2},"minecraft:custom":{"minecraft:time_since_rest":1060136,"minecraft:crouch_one_cm":1241,"minecraft:sprint_one_cm":721455,"minecraft:play_time":1060136,"minecraft:walk_one_cm":201989,"minecraft:sneak_time":992,"minecraft:drop":2,"minecraft:jump":3959,"minecraft:leave_game":30,"minecraft:time_since_death":1060136,"minecraft:interact_with_smoker":1,"minecraft:climb_one_cm":214,"minecraft:total_world_time":1162718,"minecraft:fall_one_cm":2299,"minecraft:fly_one_cm":1466979}},"DataVersion":2975}